alertg/__init__.py
alertg/app.py
test/__init__.py
test/test.py
alertg-1.0.2.dist-info/LICENSE
alertg-1.0.2.dist-info/METADATA
alertg-1.0.2.dist-info/WHEEL
alertg-1.0.2.dist-info/entry_points.txt
alertg-1.0.2.dist-info/top_level.txt
alertg-1.0.2.dist-info/RECORD
