Metadata-Version: 2.1
Name: alertg
Version: 1.0.2
Summary: UNKNOWN
Home-page: https://github.com/ayuk977/alertg
Author: Zackzonexx
Author-email: ayuk977@gmail.com
License: MIT
Project-URL: Source, https://github.com/ayuk977/alertg
Keywords: alertg
Platform: UNKNOWN
Classifier: License :: OSI Approved :: MIT License
Classifier: Programming Language :: Python :: 3
Classifier: Operating System :: OS Independent
Classifier: Development Status :: 3 - Alpha
Classifier: Intended Audience :: Developers
Classifier: Topic :: Software Development :: Libraries :: Python Modules
Classifier: Natural Language :: English
Requires-Dist: dmacheck
Requires-Dist: opsgenie-sdk
Requires-Dist: requests
Requires-Dist: urllib3
